{
  "tweet": "Attendees: keen to win this?  Check out the code off competition details here! <a href=\"https://t.co/CGcXtroq5S\" rel=\"nofollow\" dir=\"ltr\" data-expanded-url=\"http://bit.ly/29Ejrv8\" class=\"link customisable\" target=\"_blank\" title=\"http://bit.ly/29Ejrv8\" data-scribe=\"element:url\"><span class=\"u-hiddenVisually\">http://</span>bit.ly/29Ejrv8<span class=\"u-hiddenVisually\">&nbsp;</span></a> ",
  "author": "\n<div class=\"TweetAuthor\" data-scribe=\"component:author\">\n  <a class=\"TweetAuthor-link Identity u-linkBlend\" data-scribe=\"element:user_link\" href=\"https://twitter.com/jsinsa\" aria-label=\"JS in SA Conference (screen name: jsinsa)\">\n    <span class=\"TweetAuthor-avatar Identity-avatar\">\n      <img class=\"Avatar\" data-scribe=\"element:avatar\" data-src-2x=\"https://pbs.twimg.com/profile_images/444040034480439297/WuvV3-Uk_bigger.png\" alt=\"\" data-src-1x=\"https://pbs.twimg.com/profile_images/444040034480439297/WuvV3-Uk_normal.png\" src=\"https://pbs.twimg.com/profile_images/444040034480439297/WuvV3-Uk_bigger.png\">\n    </span>\n    <span class=\"TweetAuthor-name Identity-name customisable-highlight\" title=\"JS in SA Conference\" data-scribe=\"element:name\">JS in SA Conference</span>\n    \n    <span class=\"TweetAuthor-screenName Identity-screenName\" title=\"@jsinsa\" data-scribe=\"element:screen_name\" dir=\"ltr\">@jsinsa</span>\n  </a>\n</div>\n",
  "time": "\n  8h\n  ",
  "image": "https://pbs.twimg.com/media/Cm_dB46WYAA6OzW.jpg:large",
  "rt": false,
  "tid": "752062693708890112",
  "permalinkURL": "https://twitter.com/jsinsa/status/752062693708890112"
}